pretty_history/__init__.py
pretty_history/cleaning.py
pretty_history/main.py
pretty_history/prettyhist.py
pretty_history-2.0.1.dist-info/METADATA
pretty_history-2.0.1.dist-info/entry_points.txt
pretty_history-2.0.1.dist-info/WHEEL
pretty_history-2.0.1.dist-info/LICENSE
pretty_history-2.0.1.dist-info/RECORD
